README.rst
setup.py
slaveparticles/__init__.py
slaveparticles/rotor.py
slaveparticles/spins.py
slaveparticles.egg-info/PKG-INFO
slaveparticles.egg-info/SOURCES.txt
slaveparticles.egg-info/dependency_links.txt
slaveparticles.egg-info/requires.txt
slaveparticles.egg-info/top_level.txt
slaveparticles/quantum/__init__.py
slaveparticles/quantum/dos.py
slaveparticles/quantum/fermion.py
slaveparticles/quantum/operators.py
slaveparticles/quantum/spinmatrices.py
slaveparticles/utils/__init__.py
slaveparticles/utils/plotter.py
slaveparticles/utils/storage.py