Metadata-Version: 1.1
Name: slaveparticles
Version: 0.2.3.post2
Summary: Educative code on Slave Particles
Home-page: https://github.com/Titan-C/slaveparticles
Author: Óscar Nájera
Author-email: najera.oscar@gmail.com
License: GNU General Public License v3 (GPLv3)
Platform: UNKNOWN
Classifier: Intended Audience :: Developers
Classifier: Intended Audience :: Science/Research
Classifier: Programming Language :: Python
Classifier: Topic :: Scientific/Engineering
Classifier: Topic :: Software Development
